setup.py
ciex/__init__.py
ciex/ciexctl.py
ciex/ciexd.py
ciex/compat.py
ciex/context.py
ciex/core.py
ciex/error.py
ciex/util.py
ciex/version.py
ciex/worker.py
ciex.egg-info/PKG-INFO
ciex.egg-info/SOURCES.txt
ciex.egg-info/dependency_links.txt
ciex.egg-info/entry_points.txt
ciex.egg-info/requires.txt
ciex.egg-info/top_level.txt
ciex/contrib/__init__.py
ciex/contrib/workers/__init__.py
ciex/contrib/workers/elixir.py
ciex/contrib/workers/golang.py
test/test_core.py