Metadata-Version: 1.1
Name: ciex
Version: 0.1.1a0
Summary: A simple, lightweight and modular CI system
Home-page: https://github.com/walkr/ciex
Author: Tony Walker
Author-email: walkr.walkr@gmail.com
License: MIT
Platform: UNKNOWN
Classifier: License :: OSI Approved :: MIT License
Classifier: Programming Language :: Python
